vdma_lif/__init__.py
vdma_lif/models.py
vdma_lif/parser.py
vdma_lif-1.0.0.7.dist-info/METADATA
vdma_lif-1.0.0.7.dist-info/WHEEL
vdma_lif-1.0.0.7.dist-info/top_level.txt
vdma_lif-1.0.0.7.dist-info/RECORD
