Metadata-Version: 2.4
Name: vdma-lif
Version: 1.0.0.7
Summary: JSON parsers and models for the VDMA - LIF (Layout Interchange Format), which is used for defining track layouts and exchanging information between the integrator of driverless transport vehicles and a third-party master control system.
Author-email: Continua Systems GmbH <info@continua.systems>
Project-URL: Homepage, https://github.com/continua-systems/vdma-lif.git
Keywords: json,vdma,lif,vda5050
Classifier: License :: OSI Approved :: MIT License
Classifier: Programming Language :: Python
Classifier: Programming Language :: Python :: 3
Requires-Python: >=3.7
Requires-Dist: python-dateutil
Provides-Extra: dev
Requires-Dist: pip-tools; extra == "dev"
Requires-Dist: autopep8; extra == "dev"
